{"Exif":{"Lat":0,"Long":0,"Date":"2021-09-05T09:53:13-04:00","Tags":{"ApertureValue":4.375,"ComponentsConfiguration":"","CustomRendered|int":"0","DateTimeDigitized|time.Time":"2021-09-05T09:53:13-04:00","DateTimeOriginal|time.Time":"2021-09-05T09:53:13-04:00","DateTime|time.Time":"2021-09-05T09:53:13-04:00","ExposureTime|*big.Rat":"1/60","FNumber":4.5,"FocalLength":24,"ISOSpeedRatings|int":"3200","LensModel":"EF-S18-55mm f/4-5.6 IS STM","Make":"Canon","MaxApertureValue":4.362030930707784,"Model":"Canon EOS Rebel T7i","Orientation|int":"1","PixelXDimension|int":"427","PixelYDimension|int":"640","SceneCaptureType|int":"0","ShutterSpeedValue":6,"SubSecTime":"63","SubSecTimeDigitized":"63","SubSecTimeOriginal":"63"}}}
